configr/__init__.py
configr/configr.py
thumos_configr-0.0.5.dist-info/LICENSE
thumos_configr-0.0.5.dist-info/METADATA
thumos_configr-0.0.5.dist-info/WHEEL
thumos_configr-0.0.5.dist-info/top_level.txt
thumos_configr-0.0.5.dist-info/RECORD
