Metadata-Version: 2.1
Name: thumos-configr
Version: 0.0.5
Summary: Load configuration files and access them with dot-style syntax
Home-page: https://github.com/jonmest/thumos-configr/
Author: Jon Cavallie Mester
Author-email: jwcavalliemester@protonmail.com
License: UNKNOWN
Project-URL: Bug Tracker, https://github.com/jonmest/thumos-configr//issues
Platform: UNKNOWN
Classifier: Programming Language :: Python :: 3
Classifier: License :: OSI Approved :: GNU Affero General Public License v3
Classifier: Operating System :: OS Independent
Requires-Python: >=3.6
License-File: LICENSE
Requires-Dist: toml
Requires-Dist: xmltodict
